{
	"id": "9gDnBKkjvO3b2Pz",
	"json": "{\"id\":\"9gDnBKkjvO3b2Pz\",\"url\":\"https://canvas.colorado.edu/courses/123236/modules/items/6620663\",\"loadedUrl\":\"https://canvas.colorado.edu/courses/123236/assignments/2441679?module_item_id=6620663\",\"uniqueKey\":\"https://canvas.colorado.edu/courses/123236/modules/items/6620663\",\"method\":\"GET\",\"noRetry\":false,\"retryCount\":0,\"errorMessages\":[],\"headers\":{},\"userData\":{\"label\":\"course-link\",\"depth\":3,\"__crawlee\":{\"crawlDepth\":2,\"enqueueStrategy\":\"same-hostname\",\"state\":4}},\"handledAt\":\"2025-11-24T19:02:19.201Z\"}",
	"method": "GET",
	"orderNo": null,
	"retryCount": 0,
	"uniqueKey": "https://canvas.colorado.edu/courses/123236/modules/items/6620663",
	"url": "https://canvas.colorado.edu/courses/123236/modules/items/6620663"
}