{
	"id": "lxIrk8WDxtyo5tX",
	"json": "{\"id\":\"lxIrk8WDxtyo5tX\",\"url\":\"https://canvas.colorado.edu/courses/123156/files/folder/unfiled?sort=name&order=desc\",\"loadedUrl\":\"https://canvas.colorado.edu/courses/123156/files/folder/unfiled?sort=name&order=desc\",\"uniqueKey\":\"https://canvas.colorado.edu/courses/123156/files/folder/unfiled?order=desc&sort=name\",\"method\":\"GET\",\"noRetry\":false,\"retryCount\":0,\"errorMessages\":[],\"headers\":{},\"userData\":{\"type\":\"files-list\",\"__crawlee\":{\"state\":4}},\"handledAt\":\"2025-12-04T06:17:27.986Z\"}",
	"method": "GET",
	"orderNo": null,
	"retryCount": 0,
	"uniqueKey": "https://canvas.colorado.edu/courses/123156/files/folder/unfiled?order=desc&sort=name",
	"url": "https://canvas.colorado.edu/courses/123156/files/folder/unfiled?sort=name&order=desc"
}