{
	"id": "Jpldslr0MqLThIN",
	"json": "{\"id\":\"Jpldslr0MqLThIN\",\"url\":\"https://canvas.colorado.edu/courses/121531/assignments/2452613\",\"loadedUrl\":\"https://canvas.colorado.edu/courses/121531/assignments/2452613\",\"uniqueKey\":\"https://canvas.colorado.edu/courses/121531/assignments/2452613\",\"method\":\"GET\",\"noRetry\":false,\"retryCount\":0,\"errorMessages\":[],\"headers\":{},\"userData\":{\"depth\":2,\"label\":\"course-link\",\"__crawlee\":{\"crawlDepth\":2,\"enqueueStrategy\":\"same-hostname\",\"state\":4}},\"handledAt\":\"2025-12-01T05:28:34.733Z\"}",
	"method": "GET",
	"orderNo": null,
	"retryCount": 0,
	"uniqueKey": "https://canvas.colorado.edu/courses/121531/assignments/2452613",
	"url": "https://canvas.colorado.edu/courses/121531/assignments/2452613"
}