{
	"id": "vmOtOQfT0EVwRqp",
	"json": "{\"id\":\"vmOtOQfT0EVwRqp\",\"url\":\"https://canvas.colorado.edu/courses/123156?view=notifications\",\"loadedUrl\":\"https://canvas.colorado.edu/courses/123156?view=notifications\",\"uniqueKey\":\"https://canvas.colorado.edu/courses/123156?view=notifications\",\"method\":\"GET\",\"noRetry\":false,\"retryCount\":0,\"errorMessages\":[],\"headers\":{},\"userData\":{\"label\":\"course-link\",\"depth\":1,\"__crawlee\":{\"crawlDepth\":1,\"enqueueStrategy\":\"same-hostname\",\"state\":4}},\"handledAt\":\"2025-11-24T18:59:38.321Z\"}",
	"method": "GET",
	"orderNo": null,
	"retryCount": 0,
	"uniqueKey": "https://canvas.colorado.edu/courses/123156?view=notifications",
	"url": "https://canvas.colorado.edu/courses/123156?view=notifications"
}