{
	"source": "module",
	"courseId": "123236",
	"fileId": 80124799,
	"name": "Ch 07 Probset - Equities.docx",
	"moduleId": 862951,
	"moduleName": "Week 9 of 10/14",
	"modulePosition": 12,
	"moduleItemId": 6620645,
	"moduleItemTitle": "Ch 07 Probset - Equities.docx",
	"moduleItemType": "File",
	"moduleItemPosition": 6,
	"moduleItemUrl": "https://canvas.colorado.edu/courses/123236/modules/items/6620645",
	"downloadUrl": "https://canvas.colorado.edu/files/80124799/download?download_frd=1",
	"sourcePageUrl": "https://canvas.colorado.edu/courses/123236/modules/items/6620645",
	"folderPath": [
		"Modules",
		"Week 9 of 10/14"
	],
	"folderPathString": "Modules/Week 9 of 10/14",
	"indent": 0,
	"completionRequirement": null,
	"extractedAt": "2025-12-04T06:35:41.366Z"
}