{
  "requestsFinished": 177,
  "requestsFailed": 12,
  "requestsRetries": 12,
  "requestsFailedPerMinute": 2,
  "requestsFinishedPerMinute": 37,
  "requestMinDurationMillis": 1131,
  "requestMaxDurationMillis": 16209,
  "requestTotalFailedDurationMillis": 38470,
  "requestTotalFinishedDurationMillis": 988356,
  "crawlerStartedAt": "2025-11-24T18:59:19.917Z",
  "crawlerFinishedAt": "2025-11-24T19:04:07.859Z",
  "statsPersistedAt": "2025-11-24T19:04:07.859Z",
  "crawlerRuntimeMillis": 288093,
  "crawlerLastStartTimestamp": 1764010759766,
  "requestRetryHistogram": [
    177,
    null,
    null,
    12
  ],
  "statsId": 5,
  "requestAvgFailedDurationMillis": 3206,
  "requestAvgFinishedDurationMillis": 5584,
  "requestTotalDurationMillis": 1026826,
  "requestsTotal": 189,
  "requestsWithStatusCode": {
    "200": 177,
    "401": 48
  },
  "errors": {
    "/Users/karthikreddy/Downloads/GitHub/Canvas/Canvas-Wrapper/node_modules/@crawlee/basic/internals/basic-crawler.js:903:19": {
      "missing error code": {
        "Error": {
          "Request blocked - received 401 status code.": {
            "count": 12
          }
        }
      }
    }
  },
  "retryErrors": {
    "/Users/karthikreddy/Downloads/GitHub/Canvas/Canvas-Wrapper/node_modules/@crawlee/basic/internals/basic-crawler.js:903:19": {
      "missing error code": {
        "Error": {
          "Request blocked - received 401 status code.": {
            "count": 36
          }
        }
      }
    }
  }
}